opencar/__init__.py
opencar/__main__.py
opencar/py.typed
opencar/api/__init__.py
opencar/api/app.py
opencar/api/middleware/__init__.py
opencar/api/routes/__init__.py
opencar/api/schemas/__init__.py
opencar/cli/__init__.py
opencar/cli/main.py
opencar/cli/commands/__init__.py
opencar/config/__init__.py
opencar/config/settings.py
opencar/integrations/__init__.py
opencar/integrations/openai_client.py
opencar/ml/__init__.py
opencar/ml/inference/__init__.py
opencar/ml/optimization/__init__.py
opencar/ml/training/__init__.py
opencar/perception/__init__.py
opencar/perception/models/__init__.py
opencar/perception/models/detector.py
opencar/perception/processors/__init__.py
opencar/perception/utils/__init__.py
opencar/perception/utils/nms.py
opencar-1.0.1.dist-info/licenses/LICENSE
opencar-1.0.1.dist-info/METADATA
opencar-1.0.1.dist-info/WHEEL
opencar-1.0.1.dist-info/entry_points.txt
opencar-1.0.1.dist-info/top_level.txt
opencar-1.0.1.dist-info/RECORD
