Metadata-Version: 2.4
Name: opencar
Version: 1.0.1
Summary: Production-ready autonomous vehicle perception system with multimodal ML
Author-email: Nik Jois <nikjois@llamasearch.ai>
License-Expression: MIT
Project-URL: Homepage, https://github.com/llamasearchai/opencar
Project-URL: Documentation, https://github.com/llamasearchai/opencar#readme
Project-URL: Repository, https://github.com/llamasearchai/opencar
Project-URL: Issues, https://github.com/llamasearchai/opencar/issues
Classifier: Development Status :: 5 - Production/Stable
Classifier: Intended Audience :: Developers
Classifier: Programming Language :: Python :: 3
Classifier: Programming Language :: Python :: 3.10
Classifier: Programming Language :: Python :: 3.11
Classifier: Programming Language :: Python :: 3.12
Requires-Python: >=3.10
License-File: LICENSE
Requires-Dist: fastapi>=0.109.0
Requires-Dist: uvicorn[standard]>=0.27.0
Requires-Dist: pydantic>=2.5.0
Requires-Dist: pydantic-settings>=2.1.0
Requires-Dist: torch>=2.1.0
Requires-Dist: torchvision>=0.16.0
Requires-Dist: numpy>=1.24.0
Requires-Dist: opencv-python>=4.9.0
Requires-Dist: pillow>=10.2.0
Requires-Dist: openai>=1.12.0
Requires-Dist: httpx>=0.26.0
Requires-Dist: websockets>=12.0
Requires-Dist: redis>=5.0.0
Requires-Dist: sqlalchemy>=2.0.0
Requires-Dist: alembic>=1.13.0
Requires-Dist: celery>=5.3.0
Requires-Dist: prometheus-client>=0.19.0
Requires-Dist: opentelemetry-api>=1.22.0
Requires-Dist: opentelemetry-sdk>=1.22.0
Requires-Dist: opentelemetry-instrumentation-fastapi>=0.43b0
Requires-Dist: rich>=13.7.0
Requires-Dist: click>=8.1.0
Requires-Dist: typer>=0.9.0
Requires-Dist: python-multipart>=0.0.6
Requires-Dist: python-jose[cryptography]>=3.3.0
Requires-Dist: passlib[bcrypt]>=1.7.4
Requires-Dist: email-validator>=2.1.0
Requires-Dist: jinja2>=3.1.0
Requires-Dist: python-dateutil>=2.8.0
Requires-Dist: pytz>=2024.1
Requires-Dist: aiofiles>=23.2.0
Requires-Dist: aiocache>=0.12.0
Requires-Dist: structlog>=24.1.0
Requires-Dist: sentry-sdk>=1.40.0
Provides-Extra: dev
Requires-Dist: pytest>=7.4.0; extra == "dev"
Requires-Dist: pytest-asyncio>=0.23.0; extra == "dev"
Requires-Dist: pytest-cov>=4.1.0; extra == "dev"
Requires-Dist: pytest-mock>=3.12.0; extra == "dev"
Requires-Dist: pytest-benchmark>=4.0.0; extra == "dev"
Requires-Dist: hypothesis>=6.96.0; extra == "dev"
Requires-Dist: black>=24.1.0; extra == "dev"
Requires-Dist: ruff>=0.2.0; extra == "dev"
Requires-Dist: mypy>=1.8.0; extra == "dev"
Requires-Dist: isort>=5.13.0; extra == "dev"
Requires-Dist: pre-commit>=3.6.0; extra == "dev"
Requires-Dist: ipython>=8.20.0; extra == "dev"
Requires-Dist: jupyter>=1.0.0; extra == "dev"
Requires-Dist: notebook>=7.0.0; extra == "dev"
Provides-Extra: ml
Requires-Dist: transformers>=4.37.0; extra == "ml"
Requires-Dist: accelerate>=0.26.0; extra == "ml"
Requires-Dist: datasets>=2.16.0; extra == "ml"
Requires-Dist: tensorboard>=2.15.0; extra == "ml"
Requires-Dist: mlflow>=2.10.0; extra == "ml"
Requires-Dist: optuna>=3.5.0; extra == "ml"
Requires-Dist: albumentations>=1.3.0; extra == "ml"
Requires-Dist: segmentation-models-pytorch>=0.3.0; extra == "ml"
Requires-Dist: timm>=0.9.0; extra == "ml"
Dynamic: license-file
